Workbook
Name NativeTimeline_Order_date: #N/A
Name Slicer_Category: #N/A
Name Slicer_City: #N/A
Name Slicer_Gender: #N/A

Sheet Products
A1: Product_ID | B1: Product_Name | C1: Category | D1: Unit_Cost | E1: Unit_Price
A2: 1001 | B2: Headphones | C2: Electronics | D2: 380 | E2: 550
A3: 1002 | B3: Keyboard | C3: Electronics | D3: 230 | E3: 400
A4: 1003 | B4: Mouse | C4: Electronics | D4: 140 | E4: 350
A5: 1004 | B5: Speaker | C5: Electronics | D5: 230 | E5: 440
A6: 1005 | B6: Webcam | C6: Electronics | D6: 340 | E6: 520
A7: 1006 | B7: Phone Case | C7: Accessories | D7: 320 | E7: 430
A8: 1007 | B8: Charger | C8: Accessories | D8: 160 | E8: 230
A9: 1008 | B9: USB Cable | C9: Accessories | D9: 340 | E9: 430
A10: 1009 | B10: Power Bank | C10: Accessories | D10: 50 | E10: 220
A11: 1010 | B11: Laptop Sleeve | C11: Accessories | D11: 290 | E11: 470
A12: 1011 | B12: Notebook | C12: Office | D12: 120 | E12: 180
A13: 1012 | B13: Pen Set | C13: Office | D13: 380 | E13: 510
... A21: 1020 | B21: Water Bottle | C21: Fitness | D21: 400 | E21: 560

Sheet Customers
A1: Customer_ID | B1: Age | C1: Gender | D1: City
A2: 2001 | B2: 44 | C2: Male | D2: Delhi
A3: 2002 | B3: 33 | C3: Male | D3: Delhi
A4: 2003 | B4: 23 | C4: Female | D4: Bangalore
A5: 2004 | B5: 25 | C5: Male | D5: Pune
A6: 2005 | B6: 56 | C6: Female | D6: Hyderabad
A7: 2006 | B7: 32 | C7: Male | D7: Hyderabad
A8: 2007 | B8: 34 | C8: Male | D8: Bangalore
A9: 2008 | B9: 36 | C9: Male | D9: Mumbai
A10: 2009 | B10: 57 | C10: Female | D10: Pune
A11: 2010 | B11: 38 | C11: Female | D11: Mumbai
A12: 2011 | B12: 33 | C12: Female | D12: Chandigarh
A13: 2012 | B13: 21 | C13: Female | D13: Hyderabad
... A51: 2050 | B51: 54 | C51: Female | D51: Delhi

Sheet Orders
A1: Order_ID | B1: Product_ID | C1: Customer_ID | D1: Quantity
A2: 3001 | B2: 1004 | C2: 2050 | D2: 6
A3: 3002 | B3: 1015 | C3: 2031 | D3: 2
A4: 3003 | B4: 1006 | C4: 2005 | D4: 3
A5: 3004 | B5: 1014 | C5: 2042 | D5: 1
A6: 3005 | B6: 1014 | C6: 2024 | D6: 1
A7: 3006 | B7: 1004 | C7: 2001 | D7: 9
A8: 3007 | B8: 1009 | C8: 2033 | D8: 2
A9: 3008 | B9: 1019 | C9: 2011 | D9: 5
A10: 3009 | B10: 1002 | C10: 2042 | D10: 6
A11: 3010 | B11: 1016 | C11: 2004 | D11: 10
A12: 3011 | B12: 1018 | C12: 2007 | D12: 10
A13: 3012 | B13: 1008 | C13: 2034 | D13: 6
... A501: 3500 | B501: 1004 | C501: 2034 | D501: 4

Sheet Sheet1
A1: Order_date | B1: Order_ID | C1: Product_ID | D1: Customer_ID | E1: Quantity | F1: Age | G1: Gender | H1: City | I1: Product_Name | J1: Category | K1: Unit_Cost | L1: Unit_Price | M1: Cost | N1: Revenue | O1: Profit | P1: Profit_margin | Q1: Order_value_category | R1: Customer_age_group | S1: Profit_category | T1: Month
A2: 45439 | B2: 3001 | C2: 1004 | D2: 2050 | E2: 6 | F2: =VLOOKUP(Sheet1!$D2,Customers!$A$1:$D$51,2,TRUE) -> 54 | G2: =VLOOKUP(Sheet1!$D2,Customers!$A$1:$D$51,3,TRUE) -> Female | H2: =VLOOKUP(Sheet1!$D2,Customers!$A$1:$D$51,4,TRUE) -> Delhi | I2: =VLOOKUP($C2,Products!$A$1:$E$21,2,TRUE) -> Speaker | J2: =VLOOKUP($C2,Products!$A$1:$E$21,3,TRUE) -> Electronics | K2: =VLOOKUP($C2,Products!$A$1:$E$21,4,TRUE) -> 230 | L2: =VLOOKUP($C2,Products!$A$1:$E$21,5,TRUE) -> 440 | M2: =$K2*$E2 -> 1380 | N2: =$L2*$E2 -> 2640 | O2: =$N2-$M2 -> 1260 | P2: =$O2/$N2 -> 0.47727273 | Q2: =IF($N2<$N$508,"Low_order",IF($N2<$N$509,"Medium_order","High_order")) -> High_order | R2: =IF($F2<$F$508,"Young",IF($F2<$F$509,"Middle_age","Senior")) -> Senior | S2: =IF(P2<$P$508,"Low_profit",IF(P2<$P$509,"Medium_profit","High_profit")) -> High_profit | T2: =TEXT(A2,"MMM") -> May
A3: 45583 | B3: 3002 | C3: 1015 | D3: 2031 | E3: 2 | F3: =VLOOKUP(Sheet1!$D3,Customers!$A$1:$D$51,2,TRUE) -> 38 | G3: =VLOOKUP(Sheet1!$D3,Customers!$A$1:$D$51,3,TRUE) -> Male | H3: =VLOOKUP(Sheet1!$D3,Customers!$A$1:$D$51,4,TRUE) -> Bangalore | I3: =VLOOKUP($C3,Products!$A$1:$E$21,2,TRUE) -> Organizer | J3: =VLOOKUP($C3,Products!$A$1:$E$21,3,TRUE) -> Office | K3: =VLOOKUP($C3,Products!$A$1:$E$21,4,TRUE) -> 70 | L3: =VLOOKUP($C3,Products!$A$1:$E$21,5,TRUE) -> 210 | M3: =$K3*$E3 -> 140 | N3: =$L3*$E3 -> 420 | O3: =$N3-$M3 -> 280 | P3: =$O3/$N3 -> 0.66666667 | Q3: =IF($N3<$N$508,"Low_order",IF($N3<$N$509,"Medium_order","High_order")) -> Low_order | R3: =IF($F3<$F$508,"Young",IF($F3<$F$509,"Middle_age","Senior")) -> Middle_age | S3: =IF(P3<$P$508,"Low_profit",IF(P3<$P$509,"Medium_profit","High_profit")) -> High_profit | T3: =TEXT(A3,"MMM") -> Oct
A4: 45433 | B4: 3003 | C4: 1006 | D4: 2005 | E4: 3 | F4: =VLOOKUP(Sheet1!$D4,Customers!$A$1:$D$51,2,TRUE) -> 56 | G4: =VLOOKUP(Sheet1!$D4,Customers!$A$1:$D$51,3,TRUE) -> Female | H4: =VLOOKUP(Sheet1!$D4,Customers!$A$1:$D$51,4,TRUE) -> Hyderabad | I4: =VLOOKUP($C4,Products!$A$1:$E$21,2,TRUE) -> Phone Case | J4: =VLOOKUP($C4,Products!$A$1:$E$21,3,TRUE) -> Accessories | K4: =VLOOKUP($C4,Products!$A$1:$E$21,4,TRUE) -> 320 | L4: =VLOOKUP($C4,Products!$A$1:$E$21,5,TRUE) -> 430 | M4: =$K4*$E4 -> 960 | N4: =$L4*$E4 -> 1290 | O4: =$N4-$M4 -> 330 | P4: =$O4/$N4 -> 0.25581395 | Q4: =IF($N4<$N$508,"Low_order",IF($N4<$N$509,"Medium_order","High_order")) -> Medium_order | R4: =IF($F4<$F$508,"Young",IF($F4<$F$509,"Middle_age","Senior")) -> Senior | S4: =IF(P4<$P$508,"Low_profit",IF(P4<$P$509,"Medium_profit","High_profit")) -> Low_profit | T4: =TEXT(A4,"MMM") -> May
A5: 45387 | B5: 3004 | C5: 1014 | D5: 2042 | E5: 1 | F5: =VLOOKUP(Sheet1!$D5,Customers!$A$1:$D$51,2,TRUE) -> 18 | G5: =VLOOKUP(Sheet1!$D5,Customers!$A$1:$D$51,3,TRUE) -> Female | H5: =VLOOKUP(Sheet1!$D5,Customers!$A$1:$D$51,4,TRUE) -> Bangalore | I5: =VLOOKUP($C5,Products!$A$1:$E$21,2,TRUE) -> Stapler | J5: =VLOOKUP($C5,Products!$A$1:$E$21,3,TRUE) -> Office | K5: =VLOOKUP($C5,Products!$A$1:$E$21,4,TRUE) -> 170 | L5: =VLOOKUP($C5,Products!$A$1:$E$21,5,TRUE) -> 280 | M5: =$K5*$E5 -> 170 | N5: =$L5*$E5 -> 280 | O5: =$N5-$M5 -> 110 | P5: =$O5/$N5 -> 0.39285714 | Q5: =IF($N5<$N$508,"Low_order",IF($N5<$N$509,"Medium_order","High_order")) -> Low_order | R5: =IF($F5<$F$508,"Young",IF($F5<$F$509,"Middle_age","Senior")) -> Young | S5: =IF(P5<$P$508,"Low_profit",IF(P5<$P$509,"Medium_profit","High_profit")) -> Medium_profit | T5: =TEXT(A5,"MMM") -> Apr
A6: 45513 | B6: 3005 | C6: 1014 | D6: 2024 | E6: 1 | F6: =VLOOKUP(Sheet1!$D6,Customers!$A$1:$D$51,2,TRUE) -> 26 | G6: =VLOOKUP(Sheet1!$D6,Customers!$A$1:$D$51,3,TRUE) -> Female | H6: =VLOOKUP(Sheet1!$D6,Customers!$A$1:$D$51,4,TRUE) -> Delhi | I6: =VLOOKUP($C6,Products!$A$1:$E$21,2,TRUE) -> Stapler | J6: =VLOOKUP($C6,Products!$A$1:$E$21,3,TRUE) -> Office | K6: =VLOOKUP($C6,Products!$A$1:$E$21,4,TRUE) -> 170 | L6: =VLOOKUP($C6,Products!$A$1:$E$21,5,TRUE) -> 280 | M6: =$K6*$E6 -> 170 | N6: =$L6*$E6 -> 280 | O6: =$N6-$M6 -> 110 | P6: =$O6/$N6 -> 0.39285714 | Q6: =IF($N6<$N$508,"Low_order",IF($N6<$N$509,"Medium_order","High_order")) -> Low_order | R6: =IF($F6<$F$508,"Young",IF($F6<$F$509,"Middle_age","Senior")) -> Young | S6: =IF(P6<$P$508,"Low_profit",IF(P6<$P$509,"Medium_profit","High_profit")) -> Medium_profit | T6: =TEXT(A6,"MMM") -> Aug
A7: 45375 | B7: 3006 | C7: 1004 | D7: 2001 | E7: 9 | F7: =VLOOKUP(Sheet1!$D7,Customers!$A$1:$D$51,2,TRUE) -> 44 | G7: =VLOOKUP(Sheet1!$D7,Customers!$A$1:$D$51,3,TRUE) -> Male | H7: =VLOOKUP(Sheet1!$D7,Customers!$A$1:$D$51,4,TRUE) -> Delhi | I7: =VLOOKUP($C7,Products!$A$1:$E$21,2,TRUE) -> Speaker | J7: =VLOOKUP($C7,Products!$A$1:$E$21,3,TRUE) -> Electronics | K7: =VLOOKUP($C7,Products!$A$1:$E$21,4,TRUE) -> 230 | L7: =VLOOKUP($C7,Products!$A$1:$E$21,5,TRUE) -> 440 | M7: =$K7*$E7 -> 2070 | N7: =$L7*$E7 -> 3960 | O7: =$N7-$M7 -> 1890 | P7: =$O7/$N7 -> 0.47727273 | Q7: =IF($N7<$N$508,"Low_order",IF($N7<$N$509,"Medium_order","High_order")) -> High_order | R7: =IF($F7<$F$508,"Young",IF($F7<$F$509,"Middle_age","Senior")) -> Senior | S7: =IF(P7<$P$508,"Low_profit",IF(P7<$P$509,"Medium_profit","High_profit")) -> High_profit | T7: =TEXT(A7,"MMM") -> Mar
A8: 45408 | B8: 3007 | C8: 1009 | D8: 2033 | E8: 2 | F8: =VLOOKUP(Sheet1!$D8,Customers!$A$1:$D$51,2,TRUE) -> 43 | G8: =VLOOKUP(Sheet1!$D8,Customers!$A$1:$D$51,3,TRUE) -> Female | H8: =VLOOKUP(Sheet1!$D8,Customers!$A$1:$D$51,4,TRUE) -> Hyderabad | I8: =VLOOKUP($C8,Products!$A$1:$E$21,2,TRUE) -> Power Bank | J8: =VLOOKUP($C8,Products!$A$1:$E$21,3,TRUE) -> Accessories | K8: =VLOOKUP($C8,Products!$A$1:$E$21,4,TRUE) -> 50 | L8: =VLOOKUP($C8,Products!$A$1:$E$21,5,TRUE) -> 220 | M8: =$K8*$E8 -> 100 | N8: =$L8*$E8 -> 440 | O8: =$N8-$M8 -> 340 | P8: =$O8/$N8 -> 0.77272727 | Q8: =IF($N8<$N$508,"Low_order",IF($N8<$N$509,"Medium_order","High_order")) -> Low_order | R8: =IF($F8<$F$508,"Young",IF($F8<$F$509,"Middle_age","Senior")) -> Senior | S8: =IF(P8<$P$508,"Low_profit",IF(P8<$P$509,"Medium_profit","High_profit")) -> High_profit | T8: =TEXT(A8,"MMM") -> Apr
A9: 45326 | B9: 3008 | C9: 1019 | D9: 2011 | E9: 5 | F9: =VLOOKUP(Sheet1!$D9,Customers!$A$1:$D$51,2,TRUE) -> 33 | G9: =VLOOKUP(Sheet1!$D9,Customers!$A$1:$D$51,3,TRUE) -> Female | H9: =VLOOKUP(Sheet1!$D9,Customers!$A$1:$D$51,4,TRUE) -> Chandigarh | I9: =VLOOKUP($C9,Products!$A$1:$E$21,2,TRUE) -> Skipping Rope | J9: =VLOOKUP($C9,Products!$A$1:$E$21,3,TRUE) -> Fitness | K9: =VLOOKUP($C9,Products!$A$1:$E$21,4,TRUE) -> 140 | L9: =VLOOKUP($C9,Products!$A$1:$E$21,5,TRUE) -> 270 | M9: =$K9*$E9 -> 700 | N9: =$L9*$E9 -> 1350 | O9: =$N9-$M9 -> 650 | P9: =$O9/$N9 -> 0.48148148 | Q9: =IF($N9<$N$508,"Low_order",IF($N9<$N$509,"Medium_order","High_order")) -> Medium_order | R9: =IF($F9<$F$508,"Young",IF($F9<$F$509,"Middle_age","Senior")) -> Middle_age | S9: =IF(P9<$P$508,"Low_profit",IF(P9<$P$509,"Medium_profit","High_profit")) -> High_profit | T9: =TEXT(A9,"MMM") -> Feb
A10: 45335 | B10: 3009 | C10: 1002 | D10: 2042 | E10: 6 | F10: =VLOOKUP(Sheet1!$D10,Customers!$A$1:$D$51,2,TRUE) -> 18 | G10: =VLOOKUP(Sheet1!$D10,Customers!$A$1:$D$51,3,TRUE) -> Female | H10: =VLOOKUP(Sheet1!$D10,Customers!$A$1:$D$51,4,TRUE) -> Bangalore | I10: =VLOOKUP($C10,Products!$A$1:$E$21,2,TRUE) -> Keyboard | J10: =VLOOKUP($C10,Products!$A$1:$E$21,3,TRUE) -> Electronics | K10: =VLOOKUP($C10,Products!$A$1:$E$21,4,TRUE) -> 230 | L10: =VLOOKUP($C10,Products!$A$1:$E$21,5,TRUE) -> 400 | M10: =$K10*$E10 -> 1380 | N10: =$L10*$E10 -> 2400 | O10: =$N10-$M10 -> 1020 | P10: =$O10/$N10 -> 0.425 | Q10: =IF($N10<$N$508,"Low_order",IF($N10<$N$509,"Medium_order","High_order")) -> Medium_order | R10: =IF($F10<$F$508,"Young",IF($F10<$F$509,"Middle_age","Senior")) -> Young | S10: =IF(P10<$P$508,"Low_profit",IF(P10<$P$509,"Medium_profit","High_profit")) -> High_profit | T10: =TEXT(A10,"MMM") -> Feb
A11: 45405 | B11: 3010 | C11: 1016 | D11: 2004 | E11: 10 | F11: =VLOOKUP(Sheet1!$D11,Customers!$A$1:$D$51,2,TRUE) -> 25 | G11: =VLOOKUP(Sheet1!$D11,Customers!$A$1:$D$51,3,TRUE) -> Male | H11: =VLOOKUP(Sheet1!$D11,Customers!$A$1:$D$51,4,TRUE) -> Pune | I11: =VLOOKUP($C11,Products!$A$1:$E$21,2,TRUE) -> Yoga Mat | J11: =VLOOKUP($C11,Products!$A$1:$E$21,3,TRUE) -> Fitness | K11: =VLOOKUP($C11,Products!$A$1:$E$21,4,TRUE) -> 330 | L11: =VLOOKUP($C11,Products!$A$1:$E$21,5,TRUE) -> 490 | M11: =$K11*$E11 -> 3300 | N11: =$L11*$E11 -> 4900 | O11: =$N11-$M11 -> 1600 | P11: =$O11/$N11 -> 0.32653061 | Q11: =IF($N11<$N$508,"Low_order",IF($N11<$N$509,"Medium_order","High_order")) -> High_order | R11: =IF($F11<$F$508,"Young",IF($F11<$F$509,"Middle_age","Senior")) -> Young | S11: =IF(P11<$P$508,"Low_profit",IF(P11<$P$509,"Medium_profit","High_profit")) -> Medium_profit | T11: =TEXT(A11,"MMM") -> Apr
A12: 45522 | B12: 3011 | C12: 1018 | D12: 2007 | E12: 10 | F12: =VLOOKUP(Sheet1!$D12,Customers!$A$1:$D$51,2,TRUE) -> 34 | G12: =VLOOKUP(Sheet1!$D12,Customers!$A$1:$D$51,3,TRUE) -> Male | H12: =VLOOKUP(Sheet1!$D12,Customers!$A$1:$D$51,4,TRUE) -> Bangalore | I12: =VLOOKUP($C12,Products!$A$1:$E$21,2,TRUE) -> Resistance Band | J12: =VLOOKUP($C12,Products!$A$1:$E$21,3,TRUE) -> Fitness | K12: =VLOOKUP($C12,Products!$A$1:$E$21,4,TRUE) -> 310 | L12: =VLOOKUP($C12,Products!$A$1:$E$21,5,TRUE) -> 480 | M12: =$K12*$E12 -> 3100 | N12: =$L12*$E12 -> 4800 | O12: =$N12-$M12 -> 1700 | P12: =$O12/$N12 -> 0.35416667 | Q12: =IF($N12<$N$508,"Low_order",IF($N12<$N$509,"Medium_order","High_order")) -> High_order | R12: =IF($F12<$F$508,"Young",IF($F12<$F$509,"Middle_age","Senior")) -> Middle_age | S12: =IF(P12<$P$508,"Low_profit",IF(P12<$P$509,"Medium_profit","High_profit")) -> Medium_profit | T12: =TEXT(A12,"MMM") -> Aug
A13: 45366 | B13: 3012 | C13: 1008 | D13: 2034 | E13: 6 | F13: =VLOOKUP(Sheet1!$D13,Customers!$A$1:$D$51,2,TRUE) -> 48 | G13: =VLOOKUP(Sheet1!$D13,Customers!$A$1:$D$51,3,TRUE) -> Female | H13: =VLOOKUP(Sheet1!$D13,Customers!$A$1:$D$51,4,TRUE) -> Pune | I13: =VLOOKUP($C13,Products!$A$1:$E$21,2,TRUE) -> USB Cable | J13: =VLOOKUP($C13,Products!$A$1:$E$21,3,TRUE) -> Accessories | K13: =VLOOKUP($C13,Products!$A$1:$E$21,4,TRUE) -> 340 | L13: =VLOOKUP($C13,Products!$A$1:$E$21,5,TRUE) -> 430 | M13: =$K13*$E13 -> 2040 | N13: =$L13*$E13 -> 2580 | O13: =$N13-$M13 -> 540 | P13: =$O13/$N13 -> 0.20930233 | Q13: =IF($N13<$N$508,"Low_order",IF($N13<$N$509,"Medium_order","High_order")) -> High_order | R13: =IF($F13<$F$508,"Young",IF($F13<$F$509,"Middle_age","Senior")) -> Senior | S13: =IF(P13<$P$508,"Low_profit",IF(P13<$P$509,"Medium_profit","High_profit")) -> Low_profit | T13: =TEXT(A13,"MMM") -> Mar
... A501: 45630 | B501: 3500 | C501: 1004 | D501: 2034 | E501: 4 | F501: =VLOOKUP(Sheet1!$D501,Customers!$A$1:$D$51,2,TRUE) -> 48 | G501: =VLOOKUP(Sheet1!$D501,Customers!$A$1:$D$51,3,TRUE) -> Female | H501: =VLOOKUP(Sheet1!$D501,Customers!$A$1:$D$51,4,TRUE) -> Pune | I501: =VLOOKUP($C501,Products!$A$1:$E$21,2,TRUE) -> Speaker | J501: =VLOOKUP($C501,Products!$A$1:$E$21,3,TRUE) -> Electronics | K501: =VLOOKUP($C501,Products!$A$1:$E$21,4,TRUE) -> 230 | L501: =VLOOKUP($C501,Products!$A$1:$E$21,5,TRUE) -> 440 | M501: =$K501*$E501 -> 920 | N501: =$L501*$E501 -> 1760 | O501: =$N501-$M501 -> 840 | P501: =$O501/$N501 -> 0.47727273 | Q501: =IF($N501<$N$508,"Low_order",IF($N501<$N$509,"Medium_order","High_order")) -> Medium_order | R501: =IF($F501<$F$508,"Young",IF($F501<$F$509,"Middle_age","Senior")) -> Senior | S501: =IF(P501<$P$508,"Low_profit",IF(P501<$P$509,"Medium_profit","High_profit")) -> High_profit | T501: =TEXT(A501,"MMM") -> Dec
B506: =COUNT(B1:B501) -> 500 | N506: =SUM(N1:N501) -> 1025990 | O506: =SUM(O1:O501) -> 402160 | P506: =$O506/$N506 -> 0.39197263
F508: =PERCENTILE($F$1:$F$501,0.33) -> 32 | N508: =PERCENTILE($N$1:$N$501,0.33) -> 1280.1 | P508: =PERCENTILE($P$1:$P$501,0.33) -> 0.32653061
F509: =PERCENTILE($F$1:$F$501,0.66) -> 41 | N509: =PERCENTILE($N$1:$N$501,0.66) -> 2430 | P509: =PERCENTILE($P$1:$P$501,0.66) -> 0.425

Sheet Sheet2
A1: Total_Revenue | B1: 1025990
A2: Total_profit | B2: 402160
A3: Profit_margin | B3: 0.39197263
A4: Total_order | B4: 500
A5: Average_order_value | B5: =B1/B4 -> 2051.98

Sheet Sheet5
B2: Values
A3: Row Labels | B3: Sum of Revenue | C3: Sum of Profit
A4: Jan | B4: 85180 | C4: 34330
A5: Feb | B5: 96100 | C5: 35600
A6: Mar | B6: 84010 | C6: 33130
A7: Apr | B7: 93350 | C7: 38800
A8: May | B8: 92680 | C8: 35500
A9: Jun | B9: 91630 | C9: 37430
A10: Jul | B10: 76380 | C10: 31470
A11: Aug | B11: 94200 | C11: 38770
A12: Sep | B12: 75550 | C12: 27380
A13: Oct | B13: 70000 | C13: 25750
A14: Nov | B14: 77010 | C14: 29470
A15: Dec | B15: 89900 | C15: 34530
A16: Grand Total | B16: 1025990 | C16: 402160
A22: Row Labels | B22: Sum of Profit
A23: Accessories | B23: 78430
A24: Electronics | B24: 130550
A25: Fitness | B25: 103890
A26: Office | B26: 89290
A27: Grand Total | B27: 402160
A34: Row Labels | B34: Sum of Profit
A35: Bangalore | B35: 53360
A36: Chandigarh | B36: 62200
A37: Delhi | B37: 128150
A38: Hyderabad | B38: 65420
A39: Mumbai | B39: 40640
A40: Pune | B40: 52390
A41: Grand Total | B41: 402160
A45: Row Labels | B45: Sum of Revenue
A46: Middle_age | B46: 331020
A47: Senior | B47: 366970
A48: Young | B48: 328000
A49: Grand Total | B49: 1025990

Sheet Sheet3
A1: RETAIL PROFITABILITY & CUSTOMER INSIGHT ANALYSIS
A3: TOTAL_REVENUE | C3: TOTAL_PROFIT | E3: PROFIT_MARGIN | G3: TOTAL_ORDER | I3: AVG_ORDER_VALUE | K3: BEST_CATEGORY
A4: 1025990 | C4: 402160 | E4: 0.39 | G4: 500 | I4: 2051.98 | K4: ELECTRONICS
